{
  "gitSyncId": "f894a89f-593f-4400-be49-5fae01a58996_fdd40149-541c-4a79-835a-9c70b2739a16",
  "id": "First Page_Api4",
  "pluginId": "restapi-plugin",
  "pluginType": "API",
  "unpublishedAction": {
    "actionConfiguration": {
      "autoGeneratedHeaders": [
        {
          "key": "content-type",
          "value": "application/json"
        }
      ],
      "body": "{\n    \"name\": \"morpheus\",\n    \"job\": \"zion resident\"\n}",
      "bodyFormData": [],
      "encodeParamsToggle": true,
      "formData": {
        "apiContentType": "none"
      },
      "headers": [],
      "httpMethod": "PUT",
      "httpVersion": "HTTP11",
      "paginationType": "NONE",
      "path": "/api/users/2",
      "pluginSpecifiedTemplates": [
        {
          "value": true
        }
      ],
      "queryParameters": [],
      "timeoutInMillisecond": 10000
    },
    "confirmBeforeExecute": false,
    "datasource": {
      "datasourceConfiguration": {
        "url": "https://reqres.in"
      },
      "isAutoGenerated": false,
      "name": "DEFAULT_REST_DATASOURCE",
      "pluginId": "restapi-plugin"
    },
    "dynamicBindingPathList": [],
    "executeOnLoad": false,
    "name": "Api4",
    "pageId": "First Page",
    "userSetOnLoad": false
  }
}